{
  "generated_at": "2026-03-25T14:41:06.807Z",
  "posts": [
    {
      "content": "모스크바의 사이클링 축제가 개최될 예정이다. 이 축제는 도시의 사이클링 문화를促進하고, 건강한生活 방식을 홍보하는 데 목표를 두고 있다. 작년에도 많은 참가자가 모여서 즐거운 시간을 보냈고, 올해도 기대가 된다. 에라이, 이번에도 참가해봐야겠다.",
      "link": ""
    },
    {
      "content": "일본은 우크라이나를 도운 러시아에 강경 대응을 약속했다고 한다. 이는 국제적인 상황이 점점 더 복잡해지고 있는 것을 보여준다. 간지다, 각국이 서로의 이익을 위해 치열하게 경쟁을 벌이고 있다. 하지만 이러한 상황이 мир과 안전을위해 어떻게 영향을 미칠지 걱정이다.",
      "link": ""
    },
    {
      "content": "태국에서 실종된 러시아 여성들이 집단 무덤에서 발견되었다는 소식이 들렸다. 이는 매우 충격적인 뉴스이며, 그들의 가족과 친구들에게 깊은 위로를 표한다. 실화냐, 이렇게 끔찍한 사건이 발생했다니 믿기 어려울 정도다. 이러한 일을방지하기 위해 국제적인 협력이 필요하다.",
      "link": ""
    },
    {
      "content": "러시아 트럭 운전사 부족의 주요 원인은 무엇일까. 이러한 문제는 러시아 경제에 큰 영향을 미치고 있다.ㄷㄷ, 트럭 운전사의 부족으로 물류와 경제 활동에 큰 차질이 생길 수 있다.因此, 러시아 정부는 이 문제를 해결하기 위한 대책을 마련해야 한다.",
      "link": ""
    },
    {
      "content": "VTB는 이미 Post Bank 고객으로부터 대출의 절반을 이체했다고 한다. 이는 금융 산업에서 큰变化을 의미한다. 아이고, 이러한变化이 고객에게 어떻게影響을 미칠지 걱정이다. 하지만, 모든 조건은 유지되고 자동으로 전송되므로 고객들은 안심할 수 있다.",
      "link": ""
    },
    {
      "content": "모스크바에서 교통이 차단되었다는 소식이 들렸다. 이는 도시의 교통 상황을 어렵게 만들 수 있다. 에라이, 이러한 상황에 대비해서 도시의 교통 체계를 개선해야 한다. 그래야만 도시의 기능을正常하게 유지할 수 있다.",
      "link": ""
    },
    {
      "content": "러시아는 이국적인 국가에서 온 이민자들에게 관심을 가지고 있다. 이는 국제적인 상황을 반영하는 것이며, 러시아의 多様性을 증가시킬 수 있다. 간지다, 러시아가 다양한 문화와背景을 가진 사람들을 привлек하는 것은 매우 긍정적인 현상이다.",
      "link": ""
    },
    {
      "content": "이란의 두 사람이 이스라엘과 미국으로부터 면제를 받았다는 소식이 들렸다. 이는 국제적인 상황을 반영하는 것이며, 各國間의 관계가 점점 더 복잡해지고 있다. 실화냐, 이러한 상황이 어떻게 영향을 미칠지 예측하기 어렵다.",
      "link": ""
    },
    {
      "content": "러시아 여성이 북부군관구 출신 전남편에게 아파트 담보대출과 수백만 달러를 사기쳤다. 이는 매우 충격적인 뉴스이며, 법의 엄정성을 지키기 위해 이러한 범죄를 엄격하게処罰해야 한다. 아이고, 이러한 사건이 발생했다니 믿기 어려울 정도다.",
      "link": ""
    },
    {
      "content": "4월 초 모스크바에 폭우가 내릴 것으로 예상된다고 한다. 이는 도시의 날씨를 예측하기 어렵게 만들 수 있다. 에라이, 이러한 날씨에 대비해서 도시의 기반 시설을 개선해야 한다. 그래야만 도시의 기능을正常하게 유지할 수 있다. ⚡️",
      "link": ""
    },
    {
      "content": "국방부는 러시아 지역에 대한 새로운 대규모 공격을 보고했다. 이는 매우 심각한 상황이며, quốc防력을 강화하기 위해 모든 노력을 다해야 한다. 간지다, 이러한 상황에 대해 준비하고 대비해야 한다. 그래야만 국가의 안전을 유지할 수 있다.",
      "link": ""
    },
    {
      "content": "Forbes 목록의 70세 러시아 대리인이 북부 군사 지구로 떠났다고 한다. 이는 매우 뜻밖의 소식이며, 그의 결정이 어떤 영향을 미칠지 예측하기 어렵다. 실화냐, 그의 결정이 러시아 정치에 어떤 영향을 미칠지 지켜보아야 한다. 🚀",
      "link": ""
    },
    {
      "content": "러시아는 북코카서스 지역 전기 요금 미납 문제에 대해 조치하려고 한다. 이는 지역 경제에 큰 영향을 미치고 있으며, 해결해야 하는 문제이다. 아이고, 이러한 문제를 해결하기 위해 지방 정부와 중앙 정부가 협력해야 한다. 그래야만 지역 경제를 회복할 수 있다.",
      "link": ""
    },
    {
      "content": "모스크바 국방부의 방공군이 3대의 UAV를 파괴했다. 이는 매우 긍정적인 소식이며, 국가의 安全을 위한 노력이다. 에라이, 이러한 노력에 대해 긍정적으로 평가해야 한다. 그래야만 국가의 安全을 유지할 수 있다.",
      "link": ""
    },
    {
      "content": "미국은 러시아 대신 로잘린드 프랭클린을 화성에 보낼 계획이라고 한다. 이는 매우 큰 프로젝트이며, 과학 기술의 발전에 큰 영향을 미칠 수 있다. 간지다, 이러한 프로젝트가 어떻게 진행될지 지켜보아야 한다. 그래야만 과학 기술의 발전에 대한 새로운 기회를 발견할 수 있다.",
      "link": ""
    },
    {
      "content": "러시아 자동차 제조사 куб아 조립을 중단했다. 이는 러시아 경제에 영향을 미치고 있으며, 자동차 산업의 변화를 반영하는 것이다. 실화냐, 이러한 상황이 어떻게 영향을 미칠지 예측하기 어렵다. 하지만, 러시아 자동차 산업이 어떻게 대응할지 지켜보아야 한다.",
      "link": ""
    },
    {
      "content": "러시아 자동차 거대 기업이 4일 일정으로 전환이 임박했다는 사실이 알려졌다. 이는 회사 직원들에게 큰 영향을 미치고 있으며, 새로운 일정에 대해 준비해야 한다. 아이고, 이러한 변경이 회사에게 어떤 영향을 미칠지 걱정이다.하지만, 새로운 일정에 대비해서 公司가 어떻게 대응할지 지켜보아야 한다.",
      "link": ""
    }
  ]
}